taipan_assistant/__init__.py
taipan_assistant/main_cli.py
taipan_assistant/assistant/__init__.py
taipan_assistant/assistant/application.py
taipan_assistant/assistant/assistant.py
taipan_assistant/assistant/command_handler.py
taipan_assistant/assistant/error_decorator.py
taipan_assistant/assistant/output_formatter.py
taipan_assistant/contacts/__init__.py
taipan_assistant/contacts/address_book.py
taipan_assistant/contacts/record/__init__.py
taipan_assistant/contacts/record/address.py
taipan_assistant/contacts/record/birthday.py
taipan_assistant/contacts/record/email.py
taipan_assistant/contacts/record/field.py
taipan_assistant/contacts/record/name.py
taipan_assistant/contacts/record/phone.py
taipan_assistant/contacts/record/record.py
taipan_assistant/notebook/__init__.py
taipan_assistant/notebook/note.py
taipan_assistant/notebook/notebook.py
taipan_assistant/notebook/tag.py
taipan_assistant/search/__init__.py
taipan_assistant/search/engine.py
taipan_assistant-1.0.11.dist-info/METADATA
taipan_assistant-1.0.11.dist-info/WHEEL
taipan_assistant-1.0.11.dist-info/entry_points.txt
taipan_assistant-1.0.11.dist-info/RECORD
