Metadata-Version: 2.3
Name: taipan-assistant
Version: 1.0.11
Requires-Python: >=3.7
Requires-Dist: colorama==0.4.6
Requires-Dist: ngram==4.0.3
Requires-Dist: prompt-toolkit==3.0.47
Requires-Dist: wcwidth==0.2.13
